iscc/__init__.py
iscc/const.py
iscc/iscc.py
iscc/iscc.pyi
iscc-1.0.5.dist-info/LICENSE
iscc-1.0.5.dist-info/WHEEL
iscc-1.0.5.dist-info/METADATA
iscc-1.0.5.dist-info/RECORD
