Metadata-Version: 2.1
Name: iscc
Version: 1.0.5
Summary: ISCC: Reference Implementation
Home-page: https://iscc.codes/
Keywords: iscc,identifier,media,content,hash,blockchain,similarity
Author: Titusz Pan
Author-email: tp@py7.de
Requires-Python: >=3.5,<4.0
Classifier: Development Status :: 4 - Beta
Classifier: Intended Audience :: Developers
Classifier: License :: OSI Approved :: BSD License
Classifier: Natural Language :: English
Classifier: Programming Language :: Python :: 3
Classifier: Programming Language :: Python :: 3.5
Classifier: Programming Language :: Python :: 3.6
Classifier: Programming Language :: Python :: 3.7
Classifier: Programming Language :: Python :: 3.8
Requires-Dist: Pillow (>=6,<7)
Requires-Dist: xxhash (>=1,<2)
Project-URL: Repository, https://github.com/iscc/iscc-specs
